builderapk/__init__.py
builderapk/builder.py
builderapk-0.1.0.dist-info/licenses/LICENSE
builderapk-0.1.0.dist-info/METADATA
builderapk-0.1.0.dist-info/WHEEL
builderapk-0.1.0.dist-info/top_level.txt
builderapk-0.1.0.dist-info/RECORD
