Metadata-Version: 2.4
Name: builderapk
Version: 0.1.0
Summary: Pustaka Python untuk membangun proyek Android menjadi APK
Home-page: https://github.com/aternals/builderapk
Author: Eternals
Author-email: helpme.eternals@gmail.com
License: MIT
Classifier: Programming Language :: Python :: 3
Classifier: License :: OSI Approved :: MIT License
Classifier: Operating System :: OS Independent
Requires-Python: >=3.6
License-File: LICENSE
Dynamic: license-file
